Metadata-Version: 2.4
Name: one_step_frames
Version: 1.3.5
Summary: One step frame code
Author-email: Lucian Irsigler <2621933@students.wits.ac.za>
License-Expression: MIT
Project-URL: Homepage, https://github.com/lucianIrsigler/research
Project-URL: Issues, https://github.com/lucianIrsigler/research/issues
Classifier: Programming Language :: Python :: 3
Classifier: Operating System :: OS Independent
Requires-Python: >=3.9
License-File: LICENSE
Dynamic: license-file
